nova_agent/__init__.py
nova_agent/__main__.py
nova_agent/cli.py
nova_agent/config.py
nova_agent/constants.py
nova_agent/py.typed
nova_agent/settings.py
nova_agent/browser/__init__.py
nova_agent/browser/dom_extractor.py
nova_agent/browser/manager.py
nova_agent/browser/pool.py
nova_agent/executor/__init__.py
nova_agent/executor/job_manager.py
nova_agent/executor/job_session.py
nova_agent/executor/script_runner.py
nova_agent/models/__init__.py
nova_agent/models/dom.py
nova_agent/models/job.py
nova_agent/models/messages.py
nova_agent/utils/__init__.py
nova_agent/utils/domain_matcher.py
nova_agent/utils/logging.py
nova_agent/utils/system_info.py
nova_agent/websocket/__init__.py
nova_agent/websocket/client.py
nova_agent/websocket/handlers.py
nova_agent/websocket/heartbeat.py
nova_agent-0.3.8.dist-info/METADATA
nova_agent-0.3.8.dist-info/WHEEL
nova_agent-0.3.8.dist-info/entry_points.txt
nova_agent-0.3.8.dist-info/RECORD
