Metadata-Version: 2.4
Name: nova-agent
Version: 0.3.8
Summary: Nova Agent - Browser automation agent for Nova QA platform
Project-URL: Homepage, https://github.com/nova-platform/nova-agent
Project-URL: Documentation, https://docs.nova-platform.com/agent
Project-URL: Repository, https://github.com/nova-platform/nova-agent
Author: Nova Team
License-Expression: MIT
Keywords: agent,automation,browser,playwright,qa
Classifier: Development Status :: 3 - Alpha
Classifier: Environment :: Console
Classifier: Intended Audience :: Developers
Classifier: License :: OSI Approved :: MIT License
Classifier: Operating System :: OS Independent
Classifier: Programming Language :: Python :: 3
Classifier: Programming Language :: Python :: 3.11
Classifier: Programming Language :: Python :: 3.12
Classifier: Topic :: Software Development :: Testing
Requires-Python: >=3.11
Requires-Dist: httpx>=0.26.0
Requires-Dist: orjson>=3.9.0
Requires-Dist: playwright>=1.40.0
Requires-Dist: pydantic-settings>=2.0.0
Requires-Dist: pydantic>=2.5.0
Requires-Dist: python-dotenv>=1.0.0
Requires-Dist: rich>=13.0.0
Requires-Dist: structlog>=24.1.0
Requires-Dist: typer>=0.9.0
Requires-Dist: websockets>=12.0
Provides-Extra: dev
Requires-Dist: mypy>=1.8.0; extra == 'dev'
Requires-Dist: pytest-asyncio>=0.23.0; extra == 'dev'
Requires-Dist: pytest-cov>=4.1.0; extra == 'dev'
Requires-Dist: pytest>=7.4.0; extra == 'dev'
Requires-Dist: ruff>=0.1.0; extra == 'dev'
